dropstackframe/__init__.py
dropstackframe/dropstackframe.py
dropstackframe/py.typed
dropstackframe-0.1.1.dist-info/LICENSE
dropstackframe-0.1.1.dist-info/METADATA
dropstackframe-0.1.1.dist-info/WHEEL
dropstackframe-0.1.1.dist-info/RECORD
