Metadata-Version: 2.1
Name: dropstackframe
Version: 0.1.1
Summary: A python package for removing stack frames from stack traces.
Home-page: https://github.com/jesnie/dropstackframe
License: MIT
Author: Jesper Nielsen
Author-email: jespernielsen1982+dropstackframe@gmail.com
Requires-Python: >=3.10,<4
Classifier: Development Status :: 4 - Beta
Classifier: Intended Audience :: Developers
Classifier: License :: OSI Approved :: MIT License
Classifier: Programming Language :: Python :: 3
Classifier: Programming Language :: Python :: 3.10
Classifier: Programming Language :: Python :: 3.11
Classifier: Programming Language :: Python :: 3.12
Classifier: Typing :: Typed
Project-URL: Repository, https://github.com/jesnie/dropstackframe
